setup.cfg
setup.py
DSImgur.egg-info/PKG-INFO
DSImgur.egg-info/SOURCES.txt
DSImgur.egg-info/dependency_links.txt
DSImgur.egg-info/entry_points.txt
DSImgur.egg-info/not-zip-safe
DSImgur.egg-info/requires.txt
DSImgur.egg-info/top_level.txt
src/DSImgur.py
src/__init__.py