Metadata-Version: 1.0
Name: DSImgur
Version: 1.0.0.1
Summary: Easily download images, Albums, Galleries and entire Profiles from Imgur. The most powerful Imgur Downloader!! You can use as program or as module!
Home-page: https://github.com/DiSiqueira/DSImgur
Author: Diego Siqueira
Author-email: dieg0@live.com
License: MIT
Keywords: download,thread,speed,resume,multi,simple,imgur,album,gallery,images
Platform: UNKNOWN
